{"blog-essays_dl_dl linux 安装anaconda与py包.md":"Dcf8kEkF","blog-essays_index.md":"BdzsB0ZB","blog-essays_pdf list.md":"C2oDxkwu","blog-info_about.md":"B3hPR8E-","blog-info_nav.md":"DvQqrcRp","blog-info_tags.md":"cpEPaIx8","blog-posts_index.md":"W_2DScjE","blog-posts_工具杂记_adobeacrobat安装教程.md":"BpgzO7XV","blog-posts_工具杂记_excel操作汇总.md":"BFRUwjKm","blog-posts_工具杂记_inkscape 操作汇总.md":"CxTjwDCZ","blog-posts_工具杂记_ubuntu 操作记录.md":"BqsnfP0h","blog-posts_工具杂记_vmware 问题汇总.md":"CN34Ec0u","blog-posts_工具杂记_vscode markdown 导出pdf及样式设置.md":"Dt492ztG","blog-posts_工具杂记_wsl2 使用.md":"DYzRRaoI","blog-posts_工具杂记_使用spacedesk与usb将平板作为电脑副屏.md":"B49IDoOf","blog-posts_技术经验_clash verge 配置部分学术网站不走代理.md":"dMQAtwzv","blog-posts_技术经验_conda 常用命令.md":"7OY8G3i8","blog-posts_技术经验_git 常用操作.md":"CNFwGEgi","blog-posts_技术经验_latex 常用操作.md":"D_SvLKy_","blog-posts_技术经验_latex 找出bib文件中重复条目.md":"_MvTca2c","blog-posts_技术经验_nvm 安装与操作.md":"CPJ6OkV3","blog-posts_技术经验_python plotly库.md":"WEcma5Mh","blog-posts_技术经验_python 常用操作.md":"RMk6gSGV","blog-posts_技术经验_tree 生成文件树.md":"CPAgThtb","blog-posts_技术经验_vitepress 文件路径重定向.md":"BWAUXRvn","blog-posts_技术经验_vitepress 设置文档来源为部分文件夹.md":"BSKyINNa","blog-posts_技术经验_vscode latex bibtex编译错误问题.md":"BTnQLe6c","blog-posts_技术经验_vscode latex 配置.md":"BlQbxOGZ","blog-posts_技术经验_vscode 回车键 换行键 卡顿.md":"CoE4Qh8J","blog-posts_技术经验_windows 文件系统架构设计.md":"KQ8tY0LG","blog-posts_技术经验_winget 使用.md":"CuxOS2A_","blog-posts_技术经验_镜像列表.md":"B1uNomcG","blog-posts_数学理论_math 裴礼文总结.md":"CpF0DTgY","blog-posts_数学理论_math 高等代数概览.md":"sF9awkB6","blog-posts_数学理论_数学建模学习笔记.md":"Qm9k3IEx","blog-posts_日志随笔_《凡人修仙传》时间线梳理.md":"B32wRgN5","blog-posts_日志随笔_如何推荐一本书 晨星ll.md":"BYfJBsdj","index.md":"DMTCDN7h"}
